torchstruct.py
torchstruct-0.1.6.dist-info/LICENSE
torchstruct-0.1.6.dist-info/METADATA
torchstruct-0.1.6.dist-info/WHEEL
torchstruct-0.1.6.dist-info/top_level.txt
torchstruct-0.1.6.dist-info/RECORD
